{
  "ticker": "DIRR",
  "fonte": "BDI B3",
  "data_referencia": "2026-04-17",
  "capturado_em": "2026-04-19 09:22:28",
  "total_registros": 157,
  "calls": 73,
  "puts": 84,
  "semanais": 0,
  "opcoes": [
    {
      "codigo_opcao": "DIRRF180",
      "isin": "BRDIRR3F03M9",
      "ativo": "DIRR",
      "tipo": "Call",
      "semanal": false,
      "contratos_em_aberto": 123,
      "quantidade_coberta": 0,
      "quantidade_descoberta": 100,
      "total_posicoes": 1100
    },
    {
      "codigo_opcao": "DIRRF220",
      "isin": "BRDIRR3F03L1",
      "ativo": "DIRR",
      "tipo": "Call",
      "semanal": false,
      "contratos_em_aberto": 123,
      "quantidade_coberta": 0,
      "quantidade_descoberta": 0,
      "total_posicoes": 3300
    },
    {
      "codigo_opcao": "DIRRR220",
      "isin": "BRDIRR3R03L6",
      "ativo": "DIRR",
      "tipo": "Put",
      "semanal": false,
      "contratos_em_aberto": 123,
      "quantidade_coberta": 0,
      "quantidade_descoberta": 0,
      "total_posicoes": 3500
    },
    {
      "codigo_opcao": "DIRRI125",
      "isin": "BRDIRR3I0321",
      "ativo": "DIRR",
      "tipo": "Call",
      "semanal": false,
      "contratos_em_aberto": 122,
      "quantidade_coberta": 0,
      "quantidade_descoberta": 0,
      "total_posicoes": 1300
    },
    {
      "codigo_opcao": "DIRRI172",
      "isin": "BRDIRR3I0313",
      "ativo": "DIRR",
      "tipo": "Call",
      "semanal": false,
      "contratos_em_aberto": 122,
      "quantidade_coberta": 200,
      "quantidade_descoberta": 0,
      "total_posicoes": 57800
    },
    {
      "codigo_opcao": "DIRRU125",
      "isin": "BRDIRR3U0325",
      "ativo": "DIRR",
      "tipo": "Put",
      "semanal": false,
      "contratos_em_aberto": 122,
      "quantidade_coberta": 0,
      "quantidade_descoberta": 0,
      "total_posicoes": 1700
    },
    {
      "codigo_opcao": "DIRRU172",
      "isin": "BRDIRR3U0317",
      "ativo": "DIRR",
      "tipo": "Put",
      "semanal": false,
      "contratos_em_aberto": 122,
      "quantidade_coberta": 0,
      "quantidade_descoberta": 0,
      "total_posicoes": 12800
    },
    {
      "codigo_opcao": "DIRRR135",
      "isin": "BRDIRR3R04P5",
      "ativo": "DIRR",
      "tipo": "Put",
      "semanal": false,
      "contratos_em_aberto": 123,
      "quantidade_coberta": 0,
      "quantidade_descoberta": 0,
      "total_posicoes": 9300
    },
    {
      "codigo_opcao": "DIRRR140",
      "isin": "BRDIRR3R04Q3",
      "ativo": "DIRR",
      "tipo": "Put",
      "semanal": false,
      "contratos_em_aberto": 123,
      "quantidade_coberta": 0,
      "quantidade_descoberta": 1700,
      "total_posicoes": 22600
    },
    {
      "codigo_opcao": "DIRRS133",
      "isin": "BRDIRR3S03L4",
      "ativo": "DIRR",
      "tipo": "Put",
      "semanal": false,
      "contratos_em_aberto": 123,
      "quantidade_coberta": 0,
      "quantidade_descoberta": 0,
      "total_posicoes": 600
    },
    {
      "codigo_opcao": "DIRRS138",
      "isin": "BRDIRR3S03N0",
      "ativo": "DIRR",
      "tipo": "Put",
      "semanal": false,
      "contratos_em_aberto": 123,
      "quantidade_coberta": 0,
      "quantidade_descoberta": 0,
      "total_posicoes": 300
    },
    {
      "codigo_opcao": "DIRRS143",
      "isin": "BRDIRR3S03O8",
      "ativo": "DIRR",
      "tipo": "Put",
      "semanal": false,
      "contratos_em_aberto": 123,
      "quantidade_coberta": 0,
      "quantidade_descoberta": 0,
      "total_posicoes": 3700
    },
    {
      "codigo_opcao": "DIRRT128",
      "isin": "BRDIRR3T03E7",
      "ativo": "DIRR",
      "tipo": "Put",
      "semanal": false,
      "contratos_em_aberto": 123,
      "quantidade_coberta": 0,
      "quantidade_descoberta": 0,
      "total_posicoes": 600
    },
    {
      "codigo_opcao": "DIRRT133",
      "isin": "BRDIRR3T03F4",
      "ativo": "DIRR",
      "tipo": "Put",
      "semanal": false,
      "contratos_em_aberto": 123,
      "quantidade_coberta": 0,
      "quantidade_descoberta": 0,
      "total_posicoes": 400
    },
    {
      "codigo_opcao": "DIRRT138",
      "isin": "BRDIRR3T03C1",
      "ativo": "DIRR",
      "tipo": "Put",
      "semanal": false,
      "contratos_em_aberto": 123,
      "quantidade_coberta": 0,
      "quantidade_descoberta": 100,
      "total_posicoes": 1400
    },
    {
      "codigo_opcao": "DIRRP137",
      "isin": "BRDIRR3P03Z0",
      "ativo": "DIRR",
      "tipo": "Put",
      "semanal": false,
      "contratos_em_aberto": 123,
      "quantidade_coberta": 0,
      "quantidade_descoberta": 0,
      "total_posicoes": 1000
    },
    {
      "codigo_opcao": "DIRRC167",
      "isin": "BRDIRR3C03B9",
      "ativo": "DIRR",
      "tipo": "Call",
      "semanal": false,
      "contratos_em_aberto": 123,
      "quantidade_coberta": 0,
      "quantidade_descoberta": 0,
      "total_posicoes": 202600
    },
    {
      "codigo_opcao": "DIRRO167",
      "isin": "BRDIRR3O03B4",
      "ativo": "DIRR",
      "tipo": "Put",
      "semanal": false,
      "contratos_em_aberto": 123,
      "quantidade_coberta": 0,
      "quantidade_descoberta": 0,
      "total_posicoes": 200000
    },
    {
      "codigo_opcao": "DIRRI137",
      "isin": "BRDIRR3I0388",
      "ativo": "DIRR",
      "tipo": "Call",
      "semanal": false,
      "contratos_em_aberto": 123,
      "quantidade_coberta": 0,
      "quantidade_descoberta": 0,
      "total_posicoes": 44700
    },
    {
      "codigo_opcao": "DIRRI142",
      "isin": "BRDIRR3I0354",
      "ativo": "DIRR",
      "tipo": "Call",
      "semanal": false,
      "contratos_em_aberto": 123,
      "quantidade_coberta": 400,
      "quantidade_descoberta": 1000,
      "total_posicoes": 2000
    },
    {
      "codigo_opcao": "DIRRI144",
      "isin": "BRDIRR3I0347",
      "ativo": "DIRR",
      "tipo": "Call",
      "semanal": false,
      "contratos_em_aberto": 123,
      "quantidade_coberta": 0,
      "quantidade_descoberta": 0,
      "total_posicoes": 200
    },
    {
      "codigo_opcao": "DIRRI147",
      "isin": "BRDIRR3I0362",
      "ativo": "DIRR",
      "tipo": "Call",
      "semanal": false,
      "contratos_em_aberto": 123,
      "quantidade_coberta": 0,
      "quantidade_descoberta": 0,
      "total_posicoes": 1500
    },
    {
      "codigo_opcao": "DIRRU137",
      "isin": "BRDIRR3U0366",
      "ativo": "DIRR",
      "tipo": "Put",
      "semanal": false,
      "contratos_em_aberto": 123,
      "quantidade_coberta": 0,
      "quantidade_descoberta": 0,
      "total_posicoes": 12400
    },
    {
      "codigo_opcao": "DIRRU139",
      "isin": "BRDIRR3U0382",
      "ativo": "DIRR",
      "tipo": "Put",
      "semanal": false,
      "contratos_em_aberto": 123,
      "quantidade_coberta": 0,
      "quantidade_descoberta": 0,
      "total_posicoes": 5300
    },
    {
      "codigo_opcao": "DIRRA27",
      "isin": "BRDIRR3A01B7",
      "ativo": "DIRR",
      "tipo": "Call",
      "semanal": false,
      "contratos_em_aberto": 120,
      "quantidade_coberta": 0,
      "quantidade_descoberta": 0,
      "total_posicoes": 2500
    },
    {
      "codigo_opcao": "DIRRB27",
      "isin": "BRDIRR3B01F6",
      "ativo": "DIRR",
      "tipo": "Call",
      "semanal": false,
      "contratos_em_aberto": 120,
      "quantidade_coberta": 0,
      "quantidade_descoberta": 0,
      "total_posicoes": 1100
    },
    {
      "codigo_opcao": "DIRRE27",
      "isin": "BRDIRR3E0333",
      "ativo": "DIRR",
      "tipo": "Call",
      "semanal": false,
      "contratos_em_aberto": 120,
      "quantidade_coberta": 0,
      "quantidade_descoberta": 0,
      "total_posicoes": 1000
    },
    {
      "codigo_opcao": "DIRRF27",
      "isin": "BRDIRR3F02T6",
      "ativo": "DIRR",
      "tipo": "Call",
      "semanal": false,
      "contratos_em_aberto": 120,
      "quantidade_coberta": 0,
      "quantidade_descoberta": 100,
      "total_posicoes": 100
    },
    {
      "codigo_opcao": "DIRRH27",
      "isin": "BRDIRR3H0272",
      "ativo": "DIRR",
      "tipo": "Call",
      "semanal": false,
      "contratos_em_aberto": 120,
      "quantidade_coberta": 0,
      "quantidade_descoberta": 0,
      "total_posicoes": 200
    },
    {
      "codigo_opcao": "DIRRI365",
      "isin": "BRDIRR3I01Q8",
      "ativo": "DIRR",
      "tipo": "Call",
      "semanal": false,
      "contratos_em_aberto": 118,
      "quantidade_coberta": 0,
      "quantidade_descoberta": 0,
      "total_posicoes": 71900
    },
    {
      "codigo_opcao": "DIRRI405",
      "isin": "BRDIRR3I01R6",
      "ativo": "DIRR",
      "tipo": "Call",
      "semanal": false,
      "contratos_em_aberto": 118,
      "quantidade_coberta": 6000,
      "quantidade_descoberta": 0,
      "total_posicoes": 69700
    },
    {
      "codigo_opcao": "DIRRJ220",
      "isin": "BRDIRR3J0213",
      "ativo": "DIRR",
      "tipo": "Call",
      "semanal": false,
      "contratos_em_aberto": 119,
      "quantidade_coberta": 0,
      "quantidade_descoberta": 0,
      "total_posicoes": 500
    },
    {
      "codigo_opcao": "DIRRK27",
      "isin": "BRDIRR3K02D0",
      "ativo": "DIRR",
      "tipo": "Call",
      "semanal": false,
      "contratos_em_aberto": 120,
      "quantidade_coberta": 0,
      "quantidade_descoberta": 0,
      "total_posicoes": 200
    },
    {
      "codigo_opcao": "DIRRL27",
      "isin": "BRDIRR3L02L1",
      "ativo": "DIRR",
      "tipo": "Call",
      "semanal": false,
      "contratos_em_aberto": 120,
      "quantidade_coberta": 0,
      "quantidade_descoberta": 0,
      "total_posicoes": 66000
    },
    {
      "codigo_opcao": "DIRRM27",
      "isin": "BRDIRR3M01B2",
      "ativo": "DIRR",
      "tipo": "Put",
      "semanal": false,
      "contratos_em_aberto": 120,
      "quantidade_coberta": 0,
      "quantidade_descoberta": 200,
      "total_posicoes": 200
    },
    {
      "codigo_opcao": "DIRRQ27",
      "isin": "BRDIRR3Q0321",
      "ativo": "DIRR",
      "tipo": "Put",
      "semanal": false,
      "contratos_em_aberto": 120,
      "quantidade_coberta": 0,
      "quantidade_descoberta": 1400,
      "total_posicoes": 11400
    },
    {
      "codigo_opcao": "DIRRR27",
      "isin": "BRDIRR3R02T1",
      "ativo": "DIRR",
      "tipo": "Put",
      "semanal": false,
      "contratos_em_aberto": 120,
      "quantidade_coberta": 0,
      "quantidade_descoberta": 600,
      "total_posicoes": 600
    },
    {
      "codigo_opcao": "DIRRS27",
      "isin": "BRDIRR3S02E1",
      "ativo": "DIRR",
      "tipo": "Put",
      "semanal": false,
      "contratos_em_aberto": 120,
      "quantidade_coberta": 0,
      "quantidade_descoberta": 600,
      "total_posicoes": 700
    },
    {
      "codigo_opcao": "DIRRT27",
      "isin": "BRDIRR3T0278",
      "ativo": "DIRR",
      "tipo": "Put",
      "semanal": false,
      "contratos_em_aberto": 120,
      "quantidade_coberta": 0,
      "quantidade_descoberta": 200,
      "total_posicoes": 300
    },
    {
      "codigo_opcao": "DIRRU365",
      "isin": "BRDIRR3U01R1",
      "ativo": "DIRR",
      "tipo": "Put",
      "semanal": false,
      "contratos_em_aberto": 118,
      "quantidade_coberta": 0,
      "quantidade_descoberta": 4200,
      "total_posicoes": 5800
    },
    {
      "codigo_opcao": "DIRRU405",
      "isin": "BRDIRR3U01Q3",
      "ativo": "DIRR",
      "tipo": "Put",
      "semanal": false,
      "contratos_em_aberto": 118,
      "quantidade_coberta": 0,
      "quantidade_descoberta": 100,
      "total_posicoes": 100
    },
    {
      "codigo_opcao": "DIRRV220",
      "isin": "BRDIRR3V0217",
      "ativo": "DIRR",
      "tipo": "Put",
      "semanal": false,
      "contratos_em_aberto": 119,
      "quantidade_coberta": 0,
      "quantidade_descoberta": 300,
      "total_posicoes": 300
    },
    {
      "codigo_opcao": "DIRRW27",
      "isin": "BRDIRR3W02D5",
      "ativo": "DIRR",
      "tipo": "Put",
      "semanal": false,
      "contratos_em_aberto": 120,
      "quantidade_coberta": 0,
      "quantidade_descoberta": 300,
      "total_posicoes": 300
    },
    {
      "codigo_opcao": "DIRRX27",
      "isin": "BRDIRR3X02L6",
      "ativo": "DIRR",
      "tipo": "Put",
      "semanal": false,
      "contratos_em_aberto": 120,
      "quantidade_coberta": 0,
      "quantidade_descoberta": 100,
      "total_posicoes": 100
    },
    {
      "codigo_opcao": "DIRRL173",
      "isin": "BRDIRR3L03E4",
      "ativo": "DIRR",
      "tipo": "Call",
      "semanal": false,
      "contratos_em_aberto": 123,
      "quantidade_coberta": 0,
      "quantidade_descoberta": 500,
      "total_posicoes": 28300
    },
    {
      "codigo_opcao": "DIRRL183",
      "isin": "BRDIRR3L03C8",
      "ativo": "DIRR",
      "tipo": "Call",
      "semanal": false,
      "contratos_em_aberto": 123,
      "quantidade_coberta": 0,
      "quantidade_descoberta": 0,
      "total_posicoes": 3200
    },
    {
      "codigo_opcao": "DIRRL188",
      "isin": "BRDIRR3L03D6",
      "ativo": "DIRR",
      "tipo": "Call",
      "semanal": false,
      "contratos_em_aberto": 123,
      "quantidade_coberta": 0,
      "quantidade_descoberta": 0,
      "total_posicoes": 5100
    },
    {
      "codigo_opcao": "DIRRX173",
      "isin": "BRDIRR3X03E9",
      "ativo": "DIRR",
      "tipo": "Put",
      "semanal": false,
      "contratos_em_aberto": 123,
      "quantidade_coberta": 0,
      "quantidade_descoberta": 0,
      "total_posicoes": 800
    },
    {
      "codigo_opcao": "DIRRX183",
      "isin": "BRDIRR3X03C3",
      "ativo": "DIRR",
      "tipo": "Put",
      "semanal": false,
      "contratos_em_aberto": 123,
      "quantidade_coberta": 0,
      "quantidade_descoberta": 0,
      "total_posicoes": 400
    },
    {
      "codigo_opcao": "DIRRE175",
      "isin": "BRDIRR3E03N0",
      "ativo": "DIRR",
      "tipo": "Call",
      "semanal": false,
      "contratos_em_aberto": 123,
      "quantidade_coberta": 4700,
      "quantidade_descoberta": 5200,
      "total_posicoes": 63700
    },
    {
      "codigo_opcao": "DIRRI17",
      "isin": "BRDIRR3I0339",
      "ativo": "DIRR",
      "tipo": "Call",
      "semanal": false,
      "contratos_em_aberto": 123,
      "quantidade_coberta": 0,
      "quantidade_descoberta": 200,
      "total_posicoes": 1400
    },
    {
      "codigo_opcao": "DIRRW224",
      "isin": "BRDIRR3W0349",
      "ativo": "DIRR",
      "tipo": "Put",
      "semanal": false,
      "contratos_em_aberto": 123,
      "quantidade_coberta": 0,
      "quantidade_descoberta": 0,
      "total_posicoes": 2000
    },
    {
      "codigo_opcao": "DIRRX175",
      "isin": "BRDIRR3X03F6",
      "ativo": "DIRR",
      "tipo": "Put",
      "semanal": false,
      "contratos_em_aberto": 123,
      "quantidade_coberta": 0,
      "quantidade_descoberta": 0,
      "total_posicoes": 200
    },
    {
      "codigo_opcao": "DIRRB150",
      "isin": "BRDIRR3B02P3",
      "ativo": "DIRR",
      "tipo": "Call",
      "semanal": false,
      "contratos_em_aberto": 123,
      "quantidade_coberta": 0,
      "quantidade_descoberta": 0,
      "total_posicoes": 22700
    },
    {
      "codigo_opcao": "DIRRB180",
      "isin": "BRDIRR3B02R9",
      "ativo": "DIRR",
      "tipo": "Call",
      "semanal": false,
      "contratos_em_aberto": 123,
      "quantidade_coberta": 0,
      "quantidade_descoberta": 0,
      "total_posicoes": 3300
    },
    {
      "codigo_opcao": "DIRRB190",
      "isin": "BRDIRR3B02Q1",
      "ativo": "DIRR",
      "tipo": "Call",
      "semanal": false,
      "contratos_em_aberto": 123,
      "quantidade_coberta": 0,
      "quantidade_descoberta": 100,
      "total_posicoes": 2200
    },
    {
      "codigo_opcao": "DIRRN150",
      "isin": "BRDIRR3N02Q6",
      "ativo": "DIRR",
      "tipo": "Put",
      "semanal": false,
      "contratos_em_aberto": 123,
      "quantidade_coberta": 0,
      "quantidade_descoberta": 0,
      "total_posicoes": 13400
    },
    {
      "codigo_opcao": "DIRRN180",
      "isin": "BRDIRR3N02P8",
      "ativo": "DIRR",
      "tipo": "Put",
      "semanal": false,
      "contratos_em_aberto": 123,
      "quantidade_coberta": 0,
      "quantidade_descoberta": 0,
      "total_posicoes": 3000
    },
    {
      "codigo_opcao": "DIRRN190",
      "isin": "BRDIRR3N02R4",
      "ativo": "DIRR",
      "tipo": "Put",
      "semanal": false,
      "contratos_em_aberto": 123,
      "quantidade_coberta": 0,
      "quantidade_descoberta": 0,
      "total_posicoes": 6900
    },
    {
      "codigo_opcao": "DIRRE13",
      "isin": "BRDIRR3E04E7",
      "ativo": "DIRR",
      "tipo": "Call",
      "semanal": false,
      "contratos_em_aberto": 123,
      "quantidade_coberta": 5600,
      "quantidade_descoberta": 3300,
      "total_posicoes": 12700
    },
    {
      "codigo_opcao": "DIRRE14",
      "isin": "BRDIRR3E04G2",
      "ativo": "DIRR",
      "tipo": "Call",
      "semanal": false,
      "contratos_em_aberto": 123,
      "quantidade_coberta": 3700,
      "quantidade_descoberta": 39700,
      "total_posicoes": 48900
    },
    {
      "codigo_opcao": "DIRRE144",
      "isin": "BRDIRR3E04C1",
      "ativo": "DIRR",
      "tipo": "Call",
      "semanal": false,
      "contratos_em_aberto": 123,
      "quantidade_coberta": 3400,
      "quantidade_descoberta": 23100,
      "total_posicoes": 53400
    },
    {
      "codigo_opcao": "DIRRE15",
      "isin": "BRDIRR3E04D9",
      "ativo": "DIRR",
      "tipo": "Call",
      "semanal": false,
      "contratos_em_aberto": 123,
      "quantidade_coberta": 56800,
      "quantidade_descoberta": 13700,
      "total_posicoes": 125500
    },
    {
      "codigo_opcao": "DIRRE808",
      "isin": "BRDIRR3E04F4",
      "ativo": "DIRR",
      "tipo": "Call",
      "semanal": false,
      "contratos_em_aberto": 123,
      "quantidade_coberta": 0,
      "quantidade_descoberta": 0,
      "total_posicoes": 300
    },
    {
      "codigo_opcao": "DIRRQ13",
      "isin": "BRDIRR3Q04E1",
      "ativo": "DIRR",
      "tipo": "Put",
      "semanal": false,
      "contratos_em_aberto": 123,
      "quantidade_coberta": 0,
      "quantidade_descoberta": 5100,
      "total_posicoes": 84100
    },
    {
      "codigo_opcao": "DIRRQ14",
      "isin": "BRDIRR3Q04D3",
      "ativo": "DIRR",
      "tipo": "Put",
      "semanal": false,
      "contratos_em_aberto": 123,
      "quantidade_coberta": 0,
      "quantidade_descoberta": 1000,
      "total_posicoes": 77800
    },
    {
      "codigo_opcao": "DIRRQ144",
      "isin": "BRDIRR3Q04B7",
      "ativo": "DIRR",
      "tipo": "Put",
      "semanal": false,
      "contratos_em_aberto": 123,
      "quantidade_coberta": 0,
      "quantidade_descoberta": 14400,
      "total_posicoes": 59300
    },
    {
      "codigo_opcao": "DIRRQ15",
      "isin": "BRDIRR3Q04F8",
      "ativo": "DIRR",
      "tipo": "Put",
      "semanal": false,
      "contratos_em_aberto": 123,
      "quantidade_coberta": 0,
      "quantidade_descoberta": 7000,
      "total_posicoes": 30600
    },
    {
      "codigo_opcao": "DIRRQ808",
      "isin": "BRDIRR3Q04C5",
      "ativo": "DIRR",
      "tipo": "Put",
      "semanal": false,
      "contratos_em_aberto": 123,
      "quantidade_coberta": 0,
      "quantidade_descoberta": 52600,
      "total_posicoes": 57700
    },
    {
      "codigo_opcao": "DIRRE130",
      "isin": "BRDIRR3E03S9",
      "ativo": "DIRR",
      "tipo": "Call",
      "semanal": false,
      "contratos_em_aberto": 123,
      "quantidade_coberta": 13500,
      "quantidade_descoberta": 0,
      "total_posicoes": 24800
    },
    {
      "codigo_opcao": "DIRRE135",
      "isin": "BRDIRR3E03Q3",
      "ativo": "DIRR",
      "tipo": "Call",
      "semanal": false,
      "contratos_em_aberto": 123,
      "quantidade_coberta": 5500,
      "quantidade_descoberta": 92000,
      "total_posicoes": 104400
    },
    {
      "codigo_opcao": "DIRRE140",
      "isin": "BRDIRR3E03O8",
      "ativo": "DIRR",
      "tipo": "Call",
      "semanal": false,
      "contratos_em_aberto": 123,
      "quantidade_coberta": 600,
      "quantidade_descoberta": 64900,
      "total_posicoes": 69000
    },
    {
      "codigo_opcao": "DIRRE145",
      "isin": "BRDIRR3E03P5",
      "ativo": "DIRR",
      "tipo": "Call",
      "semanal": false,
      "contratos_em_aberto": 123,
      "quantidade_coberta": 400,
      "quantidade_descoberta": 7600,
      "total_posicoes": 847800
    },
    {
      "codigo_opcao": "DIRRE150",
      "isin": "BRDIRR3E03R1",
      "ativo": "DIRR",
      "tipo": "Call",
      "semanal": false,
      "contratos_em_aberto": 123,
      "quantidade_coberta": 6500,
      "quantidade_descoberta": 68800,
      "total_posicoes": 228400
    },
    {
      "codigo_opcao": "DIRRQ130",
      "isin": "BRDIRR3Q03Q7",
      "ativo": "DIRR",
      "tipo": "Put",
      "semanal": false,
      "contratos_em_aberto": 123,
      "quantidade_coberta": 0,
      "quantidade_descoberta": 1600,
      "total_posicoes": 71200
    },
    {
      "codigo_opcao": "DIRRQ135",
      "isin": "BRDIRR3Q03P9",
      "ativo": "DIRR",
      "tipo": "Put",
      "semanal": false,
      "contratos_em_aberto": 123,
      "quantidade_coberta": 0,
      "quantidade_descoberta": 6700,
      "total_posicoes": 145100
    },
    {
      "codigo_opcao": "DIRRQ140",
      "isin": "BRDIRR3Q03R5",
      "ativo": "DIRR",
      "tipo": "Put",
      "semanal": false,
      "contratos_em_aberto": 123,
      "quantidade_coberta": 0,
      "quantidade_descoberta": 0,
      "total_posicoes": 47000
    },
    {
      "codigo_opcao": "DIRRQ145",
      "isin": "BRDIRR3Q03N4",
      "ativo": "DIRR",
      "tipo": "Put",
      "semanal": false,
      "contratos_em_aberto": 123,
      "quantidade_coberta": 0,
      "quantidade_descoberta": 792300,
      "total_posicoes": 810200
    },
    {
      "codigo_opcao": "DIRRQ150",
      "isin": "BRDIRR3Q03O2",
      "ativo": "DIRR",
      "tipo": "Put",
      "semanal": false,
      "contratos_em_aberto": 123,
      "quantidade_coberta": 0,
      "quantidade_descoberta": 10000,
      "total_posicoes": 33800
    },
    {
      "codigo_opcao": "DIRRE123",
      "isin": "BRDIRR3E03X9",
      "ativo": "DIRR",
      "tipo": "Call",
      "semanal": false,
      "contratos_em_aberto": 123,
      "quantidade_coberta": 0,
      "quantidade_descoberta": 5700,
      "total_posicoes": 6300
    },
    {
      "codigo_opcao": "DIRRE128",
      "isin": "BRDIRR3E04A5",
      "ativo": "DIRR",
      "tipo": "Call",
      "semanal": false,
      "contratos_em_aberto": 123,
      "quantidade_coberta": 0,
      "quantidade_descoberta": 5400,
      "total_posicoes": 35500
    },
    {
      "codigo_opcao": "DIRRE163",
      "isin": "BRDIRR3E03Y7",
      "ativo": "DIRR",
      "tipo": "Call",
      "semanal": false,
      "contratos_em_aberto": 123,
      "quantidade_coberta": 2600,
      "quantidade_descoberta": 29500,
      "total_posicoes": 136200
    },
    {
      "codigo_opcao": "DIRRE168",
      "isin": "BRDIRR3E0473",
      "ativo": "DIRR",
      "tipo": "Call",
      "semanal": false,
      "contratos_em_aberto": 123,
      "quantidade_coberta": 9600,
      "quantidade_descoberta": 31100,
      "total_posicoes": 57900
    },
    {
      "codigo_opcao": "DIRRE173",
      "isin": "BRDIRR3E03Z4",
      "ativo": "DIRR",
      "tipo": "Call",
      "semanal": false,
      "contratos_em_aberto": 123,
      "quantidade_coberta": 0,
      "quantidade_descoberta": 9800,
      "total_posicoes": 12800
    },
    {
      "codigo_opcao": "DIRRE178",
      "isin": "BRDIRR3E0432",
      "ativo": "DIRR",
      "tipo": "Call",
      "semanal": false,
      "contratos_em_aberto": 123,
      "quantidade_coberta": 1200,
      "quantidade_descoberta": 0,
      "total_posicoes": 11400
    },
    {
      "codigo_opcao": "DIRRE188",
      "isin": "BRDIRR3E0416",
      "ativo": "DIRR",
      "tipo": "Call",
      "semanal": false,
      "contratos_em_aberto": 123,
      "quantidade_coberta": 0,
      "quantidade_descoberta": 2000,
      "total_posicoes": 2400
    },
    {
      "codigo_opcao": "DIRRE193",
      "isin": "BRDIRR3E0457",
      "ativo": "DIRR",
      "tipo": "Call",
      "semanal": false,
      "contratos_em_aberto": 123,
      "quantidade_coberta": 0,
      "quantidade_descoberta": 900,
      "total_posicoes": 900
    },
    {
      "codigo_opcao": "DIRRQ103",
      "isin": "BRDIRR3Q0487",
      "ativo": "DIRR",
      "tipo": "Put",
      "semanal": false,
      "contratos_em_aberto": 123,
      "quantidade_coberta": 0,
      "quantidade_descoberta": 65200,
      "total_posicoes": 73600
    },
    {
      "codigo_opcao": "DIRRQ108",
      "isin": "BRDIRR3Q0446",
      "ativo": "DIRR",
      "tipo": "Put",
      "semanal": false,
      "contratos_em_aberto": 123,
      "quantidade_coberta": 0,
      "quantidade_descoberta": 7900,
      "total_posicoes": 16100
    },
    {
      "codigo_opcao": "DIRRQ113",
      "isin": "BRDIRR3Q0412",
      "ativo": "DIRR",
      "tipo": "Put",
      "semanal": false,
      "contratos_em_aberto": 123,
      "quantidade_coberta": 0,
      "quantidade_descoberta": 0,
      "total_posicoes": 37300
    },
    {
      "codigo_opcao": "DIRRQ118",
      "isin": "BRDIRR3Q03W5",
      "ativo": "DIRR",
      "tipo": "Put",
      "semanal": false,
      "contratos_em_aberto": 123,
      "quantidade_coberta": 0,
      "quantidade_descoberta": 0,
      "total_posicoes": 239200
    },
    {
      "codigo_opcao": "DIRRQ123",
      "isin": "BRDIRR3Q0461",
      "ativo": "DIRR",
      "tipo": "Put",
      "semanal": false,
      "contratos_em_aberto": 123,
      "quantidade_coberta": 0,
      "quantidade_descoberta": 300,
      "total_posicoes": 63900
    },
    {
      "codigo_opcao": "DIRRQ128",
      "isin": "BRDIRR3Q0453",
      "ativo": "DIRR",
      "tipo": "Put",
      "semanal": false,
      "contratos_em_aberto": 123,
      "quantidade_coberta": 0,
      "quantidade_descoberta": 13100,
      "total_posicoes": 154300
    },
    {
      "codigo_opcao": "DIRRQ163",
      "isin": "BRDIRR3Q0479",
      "ativo": "DIRR",
      "tipo": "Put",
      "semanal": false,
      "contratos_em_aberto": 123,
      "quantidade_coberta": 0,
      "quantidade_descoberta": 0,
      "total_posicoes": 32800
    },
    {
      "codigo_opcao": "DIRRQ168",
      "isin": "BRDIRR3Q03Y1",
      "ativo": "DIRR",
      "tipo": "Put",
      "semanal": false,
      "contratos_em_aberto": 123,
      "quantidade_coberta": 0,
      "quantidade_descoberta": 2500,
      "total_posicoes": 28700
    },
    {
      "codigo_opcao": "DIRRQ173",
      "isin": "BRDIRR3Q03V7",
      "ativo": "DIRR",
      "tipo": "Put",
      "semanal": false,
      "contratos_em_aberto": 123,
      "quantidade_coberta": 0,
      "quantidade_descoberta": 2000,
      "total_posicoes": 3100
    },
    {
      "codigo_opcao": "DIRRQ188",
      "isin": "BRDIRR3Q04A9",
      "ativo": "DIRR",
      "tipo": "Put",
      "semanal": false,
      "contratos_em_aberto": 123,
      "quantidade_coberta": 0,
      "quantidade_descoberta": 0,
      "total_posicoes": 300
    },
    {
      "codigo_opcao": "DIRRQ193",
      "isin": "BRDIRR3Q0404",
      "ativo": "DIRR",
      "tipo": "Put",
      "semanal": false,
      "contratos_em_aberto": 123,
      "quantidade_coberta": 0,
      "quantidade_descoberta": 0,
      "total_posicoes": 800
    },
    {
      "codigo_opcao": "DIRRQ918",
      "isin": "BRDIRR3Q03T1",
      "ativo": "DIRR",
      "tipo": "Put",
      "semanal": false,
      "contratos_em_aberto": 123,
      "quantidade_coberta": 0,
      "quantidade_descoberta": 0,
      "total_posicoes": 15000
    },
    {
      "codigo_opcao": "DIRRQ938",
      "isin": "BRDIRR3Q03Z8",
      "ativo": "DIRR",
      "tipo": "Put",
      "semanal": false,
      "contratos_em_aberto": 123,
      "quantidade_coberta": 0,
      "quantidade_descoberta": 0,
      "total_posicoes": 7000
    },
    {
      "codigo_opcao": "DIRRQ958",
      "isin": "BRDIRR3Q0495",
      "ativo": "DIRR",
      "tipo": "Put",
      "semanal": false,
      "contratos_em_aberto": 123,
      "quantidade_coberta": 0,
      "quantidade_descoberta": 0,
      "total_posicoes": 5000
    },
    {
      "codigo_opcao": "DIRRQ978",
      "isin": "BRDIRR3Q03S3",
      "ativo": "DIRR",
      "tipo": "Put",
      "semanal": false,
      "contratos_em_aberto": 123,
      "quantidade_coberta": 0,
      "quantidade_descoberta": 4100,
      "total_posicoes": 4100
    },
    {
      "codigo_opcao": "DIRRQ998",
      "isin": "BRDIRR3Q03U9",
      "ativo": "DIRR",
      "tipo": "Put",
      "semanal": false,
      "contratos_em_aberto": 123,
      "quantidade_coberta": 0,
      "quantidade_descoberta": 1100,
      "total_posicoes": 3100
    },
    {
      "codigo_opcao": "DIRRK205",
      "isin": "BRDIRR3K0335",
      "ativo": "DIRR",
      "tipo": "Call",
      "semanal": false,
      "contratos_em_aberto": 122,
      "quantidade_coberta": 0,
      "quantidade_descoberta": 0,
      "total_posicoes": 24300
    },
    {
      "codigo_opcao": "DIRRW205",
      "isin": "BRDIRR3W0331",
      "ativo": "DIRR",
      "tipo": "Put",
      "semanal": false,
      "contratos_em_aberto": 122,
      "quantidade_coberta": 0,
      "quantidade_descoberta": 0,
      "total_posicoes": 7500
    },
    {
      "codigo_opcao": "DIRRE134",
      "isin": "BRDIRR3E04H0",
      "ativo": "DIRR",
      "tipo": "Call",
      "semanal": false,
      "contratos_em_aberto": 123,
      "quantidade_coberta": 0,
      "quantidade_descoberta": 0,
      "total_posicoes": 5100
    },
    {
      "codigo_opcao": "DIRRQ134",
      "isin": "BRDIRR3Q04G6",
      "ativo": "DIRR",
      "tipo": "Put",
      "semanal": false,
      "contratos_em_aberto": 123,
      "quantidade_coberta": 0,
      "quantidade_descoberta": 0,
      "total_posicoes": 31900
    },
    {
      "codigo_opcao": "DIRRB31",
      "isin": "BRDIRR3B02O6",
      "ativo": "DIRR",
      "tipo": "Call",
      "semanal": false,
      "contratos_em_aberto": 123,
      "quantidade_coberta": 0,
      "quantidade_descoberta": 0,
      "total_posicoes": 24400
    },
    {
      "codigo_opcao": "DIRRN31",
      "isin": "BRDIRR3N02O1",
      "ativo": "DIRR",
      "tipo": "Put",
      "semanal": false,
      "contratos_em_aberto": 123,
      "quantidade_coberta": 0,
      "quantidade_descoberta": 0,
      "total_posicoes": 3600
    },
    {
      "codigo_opcao": "DIRRF145",
      "isin": "BRDIRR3F03R8",
      "ativo": "DIRR",
      "tipo": "Call",
      "semanal": false,
      "contratos_em_aberto": 123,
      "quantidade_coberta": 32200,
      "quantidade_descoberta": 25700,
      "total_posicoes": 186300
    },
    {
      "codigo_opcao": "DIRRF150",
      "isin": "BRDIRR3F03Q0",
      "ativo": "DIRR",
      "tipo": "Call",
      "semanal": false,
      "contratos_em_aberto": 123,
      "quantidade_coberta": 200,
      "quantidade_descoberta": 7700,
      "total_posicoes": 75000
    },
    {
      "codigo_opcao": "DIRRF155",
      "isin": "BRDIRR3F03S6",
      "ativo": "DIRR",
      "tipo": "Call",
      "semanal": false,
      "contratos_em_aberto": 123,
      "quantidade_coberta": 0,
      "quantidade_descoberta": 3800,
      "total_posicoes": 58100
    },
    {
      "codigo_opcao": "DIRRF160",
      "isin": "BRDIRR3F03O5",
      "ativo": "DIRR",
      "tipo": "Call",
      "semanal": false,
      "contratos_em_aberto": 123,
      "quantidade_coberta": 0,
      "quantidade_descoberta": 21600,
      "total_posicoes": 199800
    },
    {
      "codigo_opcao": "DIRRF165",
      "isin": "BRDIRR3F03U2",
      "ativo": "DIRR",
      "tipo": "Call",
      "semanal": false,
      "contratos_em_aberto": 123,
      "quantidade_coberta": 100,
      "quantidade_descoberta": 28200,
      "total_posicoes": 55600
    },
    {
      "codigo_opcao": "DIRRF170",
      "isin": "BRDIRR3F03P2",
      "ativo": "DIRR",
      "tipo": "Call",
      "semanal": false,
      "contratos_em_aberto": 123,
      "quantidade_coberta": 600,
      "quantidade_descoberta": 26100,
      "total_posicoes": 61200
    },
    {
      "codigo_opcao": "DIRRF175",
      "isin": "BRDIRR3F03T4",
      "ativo": "DIRR",
      "tipo": "Call",
      "semanal": false,
      "contratos_em_aberto": 123,
      "quantidade_coberta": 0,
      "quantidade_descoberta": 0,
      "total_posicoes": 12300
    },
    {
      "codigo_opcao": "DIRRR145",
      "isin": "BRDIRR3R03U7",
      "ativo": "DIRR",
      "tipo": "Put",
      "semanal": false,
      "contratos_em_aberto": 123,
      "quantidade_coberta": 0,
      "quantidade_descoberta": 500,
      "total_posicoes": 36500
    },
    {
      "codigo_opcao": "DIRRR150",
      "isin": "BRDIRR3R03P7",
      "ativo": "DIRR",
      "tipo": "Put",
      "semanal": false,
      "contratos_em_aberto": 123,
      "quantidade_coberta": 0,
      "quantidade_descoberta": 0,
      "total_posicoes": 20200
    },
    {
      "codigo_opcao": "DIRRR155",
      "isin": "BRDIRR3R03Q5",
      "ativo": "DIRR",
      "tipo": "Put",
      "semanal": false,
      "contratos_em_aberto": 123,
      "quantidade_coberta": 0,
      "quantidade_descoberta": 681100,
      "total_posicoes": 697600
    },
    {
      "codigo_opcao": "DIRRR170",
      "isin": "BRDIRR3R03O0",
      "ativo": "DIRR",
      "tipo": "Put",
      "semanal": false,
      "contratos_em_aberto": 123,
      "quantidade_coberta": 0,
      "quantidade_descoberta": 0,
      "total_posicoes": 700
    },
    {
      "codigo_opcao": "DIRRK142",
      "isin": "BRDIRR3K0350",
      "ativo": "DIRR",
      "tipo": "Call",
      "semanal": false,
      "contratos_em_aberto": 123,
      "quantidade_coberta": 0,
      "quantidade_descoberta": 100,
      "total_posicoes": 3700
    },
    {
      "codigo_opcao": "DIRRK147",
      "isin": "BRDIRR3K0384",
      "ativo": "DIRR",
      "tipo": "Call",
      "semanal": false,
      "contratos_em_aberto": 123,
      "quantidade_coberta": 0,
      "quantidade_descoberta": 0,
      "total_posicoes": 1000
    },
    {
      "codigo_opcao": "DIRRK152",
      "isin": "BRDIRR3K03F3",
      "ativo": "DIRR",
      "tipo": "Call",
      "semanal": false,
      "contratos_em_aberto": 123,
      "quantidade_coberta": 0,
      "quantidade_descoberta": 0,
      "total_posicoes": 700
    },
    {
      "codigo_opcao": "DIRRW142",
      "isin": "BRDIRR3W0380",
      "ativo": "DIRR",
      "tipo": "Put",
      "semanal": false,
      "contratos_em_aberto": 123,
      "quantidade_coberta": 0,
      "quantidade_descoberta": 0,
      "total_posicoes": 5900
    },
    {
      "codigo_opcao": "DIRRW147",
      "isin": "BRDIRR3W03D3",
      "ativo": "DIRR",
      "tipo": "Put",
      "semanal": false,
      "contratos_em_aberto": 123,
      "quantidade_coberta": 0,
      "quantidade_descoberta": 0,
      "total_posicoes": 7300
    },
    {
      "codigo_opcao": "DIRRW167",
      "isin": "BRDIRR3W03B7",
      "ativo": "DIRR",
      "tipo": "Put",
      "semanal": false,
      "contratos_em_aberto": 123,
      "quantidade_coberta": 0,
      "quantidade_descoberta": 0,
      "total_posicoes": 1100
    },
    {
      "codigo_opcao": "DIRRW187",
      "isin": "BRDIRR3W0398",
      "ativo": "DIRR",
      "tipo": "Put",
      "semanal": false,
      "contratos_em_aberto": 123,
      "quantidade_coberta": 0,
      "quantidade_descoberta": 0,
      "total_posicoes": 5200
    },
    {
      "codigo_opcao": "DIRRW197",
      "isin": "BRDIRR3W03E1",
      "ativo": "DIRR",
      "tipo": "Put",
      "semanal": false,
      "contratos_em_aberto": 123,
      "quantidade_coberta": 0,
      "quantidade_descoberta": 0,
      "total_posicoes": 22600
    },
    {
      "codigo_opcao": "DIRRC162",
      "isin": "BRDIRR3C03A1",
      "ativo": "DIRR",
      "tipo": "Call",
      "semanal": false,
      "contratos_em_aberto": 123,
      "quantidade_coberta": 0,
      "quantidade_descoberta": 0,
      "total_posicoes": 309000
    },
    {
      "codigo_opcao": "DIRRO162",
      "isin": "BRDIRR3O03A6",
      "ativo": "DIRR",
      "tipo": "Put",
      "semanal": false,
      "contratos_em_aberto": 123,
      "quantidade_coberta": 0,
      "quantidade_descoberta": 0,
      "total_posicoes": 305500
    },
    {
      "codigo_opcao": "DIRRF108",
      "isin": "BRDIRR3F03W8",
      "ativo": "DIRR",
      "tipo": "Call",
      "semanal": false,
      "contratos_em_aberto": 123,
      "quantidade_coberta": 0,
      "quantidade_descoberta": 6900,
      "total_posicoes": 6900
    },
    {
      "codigo_opcao": "DIRRF113",
      "isin": "BRDIRR3F03V0",
      "ativo": "DIRR",
      "tipo": "Call",
      "semanal": false,
      "contratos_em_aberto": 123,
      "quantidade_coberta": 1000,
      "quantidade_descoberta": 12200,
      "total_posicoes": 15200
    },
    {
      "codigo_opcao": "DIRRR108",
      "isin": "BRDIRR3R03W3",
      "ativo": "DIRR",
      "tipo": "Put",
      "semanal": false,
      "contratos_em_aberto": 123,
      "quantidade_coberta": 0,
      "quantidade_descoberta": 600,
      "total_posicoes": 23500
    },
    {
      "codigo_opcao": "DIRRR113",
      "isin": "BRDIRR3R03V5",
      "ativo": "DIRR",
      "tipo": "Put",
      "semanal": false,
      "contratos_em_aberto": 123,
      "quantidade_coberta": 0,
      "quantidade_descoberta": 0,
      "total_posicoes": 5900
    },
    {
      "codigo_opcao": "DIRRF123",
      "isin": "BRDIRR3F04A2",
      "ativo": "DIRR",
      "tipo": "Call",
      "semanal": false,
      "contratos_em_aberto": 123,
      "quantidade_coberta": 100,
      "quantidade_descoberta": 0,
      "total_posicoes": 500
    },
    {
      "codigo_opcao": "DIRRF138",
      "isin": "BRDIRR3F0407",
      "ativo": "DIRR",
      "tipo": "Call",
      "semanal": false,
      "contratos_em_aberto": 123,
      "quantidade_coberta": 0,
      "quantidade_descoberta": 0,
      "total_posicoes": 2900
    },
    {
      "codigo_opcao": "DIRRF143",
      "isin": "BRDIRR3F0464",
      "ativo": "DIRR",
      "tipo": "Call",
      "semanal": false,
      "contratos_em_aberto": 123,
      "quantidade_coberta": 0,
      "quantidade_descoberta": 12700,
      "total_posicoes": 13300
    },
    {
      "codigo_opcao": "DIRRF153",
      "isin": "BRDIRR3F04D6",
      "ativo": "DIRR",
      "tipo": "Call",
      "semanal": false,
      "contratos_em_aberto": 123,
      "quantidade_coberta": 8500,
      "quantidade_descoberta": 0,
      "total_posicoes": 25300
    },
    {
      "codigo_opcao": "DIRRF158",
      "isin": "BRDIRR3F04K1",
      "ativo": "DIRR",
      "tipo": "Call",
      "semanal": false,
      "contratos_em_aberto": 123,
      "quantidade_coberta": 0,
      "quantidade_descoberta": 300,
      "total_posicoes": 14100
    },
    {
      "codigo_opcao": "DIRRF163",
      "isin": "BRDIRR3F0472",
      "ativo": "DIRR",
      "tipo": "Call",
      "semanal": false,
      "contratos_em_aberto": 123,
      "quantidade_coberta": 0,
      "quantidade_descoberta": 0,
      "total_posicoes": 400
    },
    {
      "codigo_opcao": "DIRRF168",
      "isin": "BRDIRR3F0431",
      "ativo": "DIRR",
      "tipo": "Call",
      "semanal": false,
      "contratos_em_aberto": 123,
      "quantidade_coberta": 0,
      "quantidade_descoberta": 0,
      "total_posicoes": 2000
    },
    {
      "codigo_opcao": "DIRRF178",
      "isin": "BRDIRR3F04I5",
      "ativo": "DIRR",
      "tipo": "Call",
      "semanal": false,
      "contratos_em_aberto": 123,
      "quantidade_coberta": 0,
      "quantidade_descoberta": 0,
      "total_posicoes": 3000
    },
    {
      "codigo_opcao": "DIRRF188",
      "isin": "BRDIRR3F03Z1",
      "ativo": "DIRR",
      "tipo": "Call",
      "semanal": false,
      "contratos_em_aberto": 123,
      "quantidade_coberta": 0,
      "quantidade_descoberta": 0,
      "total_posicoes": 200
    },
    {
      "codigo_opcao": "DIRRR123",
      "isin": "BRDIRR3R04D1",
      "ativo": "DIRR",
      "tipo": "Put",
      "semanal": false,
      "contratos_em_aberto": 123,
      "quantidade_coberta": 0,
      "quantidade_descoberta": 0,
      "total_posicoes": 100
    },
    {
      "codigo_opcao": "DIRRR128",
      "isin": "BRDIRR3R04O8",
      "ativo": "DIRR",
      "tipo": "Put",
      "semanal": false,
      "contratos_em_aberto": 123,
      "quantidade_coberta": 0,
      "quantidade_descoberta": 5300,
      "total_posicoes": 15000
    },
    {
      "codigo_opcao": "DIRRR133",
      "isin": "BRDIRR3R04I0",
      "ativo": "DIRR",
      "tipo": "Put",
      "semanal": false,
      "contratos_em_aberto": 123,
      "quantidade_coberta": 0,
      "quantidade_descoberta": 0,
      "total_posicoes": 8600
    },
    {
      "codigo_opcao": "DIRRR138",
      "isin": "BRDIRR3R04N0",
      "ativo": "DIRR",
      "tipo": "Put",
      "semanal": false,
      "contratos_em_aberto": 123,
      "quantidade_coberta": 0,
      "quantidade_descoberta": 0,
      "total_posicoes": 14500
    },
    {
      "codigo_opcao": "DIRRR143",
      "isin": "BRDIRR3R0486",
      "ativo": "DIRR",
      "tipo": "Put",
      "semanal": false,
      "contratos_em_aberto": 123,
      "quantidade_coberta": 0,
      "quantidade_descoberta": 424300,
      "total_posicoes": 738200
    },
    {
      "codigo_opcao": "DIRRR153",
      "isin": "BRDIRR3R0460",
      "ativo": "DIRR",
      "tipo": "Put",
      "semanal": false,
      "contratos_em_aberto": 123,
      "quantidade_coberta": 0,
      "quantidade_descoberta": 8000,
      "total_posicoes": 8400
    },
    {
      "codigo_opcao": "DIRRR158",
      "isin": "BRDIRR3R0494",
      "ativo": "DIRR",
      "tipo": "Put",
      "semanal": false,
      "contratos_em_aberto": 123,
      "quantidade_coberta": 0,
      "quantidade_descoberta": 0,
      "total_posicoes": 200
    },
    {
      "codigo_opcao": "DIRRR163",
      "isin": "BRDIRR3R04A7",
      "ativo": "DIRR",
      "tipo": "Put",
      "semanal": false,
      "contratos_em_aberto": 123,
      "quantidade_coberta": 0,
      "quantidade_descoberta": 0,
      "total_posicoes": 2000
    },
    {
      "codigo_opcao": "DIRRE158",
      "isin": "BRDIRR3E03M2",
      "ativo": "DIRR",
      "tipo": "Call",
      "semanal": false,
      "contratos_em_aberto": 123,
      "quantidade_coberta": 10800,
      "quantidade_descoberta": 16500,
      "total_posicoes": 46700
    },
    {
      "codigo_opcao": "DIRRQ158",
      "isin": "BRDIRR3Q03L8",
      "ativo": "DIRR",
      "tipo": "Put",
      "semanal": false,
      "contratos_em_aberto": 123,
      "quantidade_coberta": 0,
      "quantidade_descoberta": 0,
      "total_posicoes": 65000
    },
    {
      "codigo_opcao": "DIRRF130",
      "isin": "BRDIRR3F03K3",
      "ativo": "DIRR",
      "tipo": "Call",
      "semanal": false,
      "contratos_em_aberto": 123,
      "quantidade_coberta": 12500,
      "quantidade_descoberta": 9800,
      "total_posicoes": 164400
    },
    {
      "codigo_opcao": "DIRRR130",
      "isin": "BRDIRR3R03K8",
      "ativo": "DIRR",
      "tipo": "Put",
      "semanal": false,
      "contratos_em_aberto": 123,
      "quantidade_coberta": 0,
      "quantidade_descoberta": 32400,
      "total_posicoes": 157600
    },
    {
      "codigo_opcao": "DIRRF148",
      "isin": "BRDIRR3F03X6",
      "ativo": "DIRR",
      "tipo": "Call",
      "semanal": false,
      "contratos_em_aberto": 123,
      "quantidade_coberta": 0,
      "quantidade_descoberta": 0,
      "total_posicoes": 280900
    },
    {
      "codigo_opcao": "DIRRR148",
      "isin": "BRDIRR3R03X1",
      "ativo": "DIRR",
      "tipo": "Put",
      "semanal": false,
      "contratos_em_aberto": 123,
      "quantidade_coberta": 0,
      "quantidade_descoberta": 10900,
      "total_posicoes": 21700
    }
  ]
}